web/__init__.py
web/app.py
web/cli.py
web/env/__init__.py
web/env/database/__init__.py
web/env/database/access.py
web/env/database/database.py
web/env/database/model_loader.py
web/env/database/models.py
web/env/database/utils.py
web/errors/__init__.py
web/errors/app.py
web/errors/files.py
web/errors/http.py
web/errors/metrics.py
web/kernel/__init__.py
web/kernel/messaging/__init__.py
web/kernel/messaging/channel.py
web/kernel/messaging/dispatcher.py
web/kernel/proc/__init__.py
web/kernel/proc/isolate.py
web/kernel/proc/manager.py
web/kernel/proc/scheduler.py
web/kernel/signal.py
web/kernel/tracing/OT_tracer.py
web/kernel/tracing/__init__.py
web/kernel/tracing/base_tracer.py
web/kernel/transport.py
web/kernel/types.py
web/sanic_test.py
web/settings.py
web/test.py
web/trend/__init__.py
web/trend/grpc/__init__.py
web/trend/grpc/transport.py
web/trend/rest/__init__.py
web/trend/rest/custom.py
web/trend/rest/sse.py
web/trend/rest/transport.py
web/trend/rest/utils/__init__.py
web/trend/rest/utils/openapi.py
web/trend/rest/utils/openapi_gen.py
web/trend/rest/utils/openapi_spec.py
web/trend/rest/ws.py
web/utils/__init__.py
web/utils/crypto.py
web/utils/helpers.py
web/utils/logger.py
web/utils/socket_logger.py
web_foundation-3.0.57.dist-info/METADATA
web_foundation-3.0.57.dist-info/WHEEL
web_foundation-3.0.57.dist-info/RECORD
